edgeprot_api/__init__.py
edgeprot_api/client.py
edgeprot_api/endpoints.py
edgeprot_api/exceptions.py
edgeprot_api/models.py
edgeprot_client-0.1.3.dist-info/licenses/LICENSE
edgeprot_client-0.1.3.dist-info/METADATA
edgeprot_client-0.1.3.dist-info/WHEEL
edgeprot_client-0.1.3.dist-info/top_level.txt
edgeprot_client-0.1.3.dist-info/RECORD
