Metadata-Version: 2.4
Name: edgeprot-client
Version: 0.1.3
Summary: A Python API client for interacting with the EdgeProt API.
Author-email: Poly Anthi <edgeprotclient@thepoly.eu>
License: MIT
Keywords: API,client,EdgeProt
Classifier: Programming Language :: Python :: 3
Classifier: License :: OSI Approved :: MIT License
Classifier: Operating System :: OS Independent
Classifier: Intended Audience :: Developers
Classifier: Topic :: Software Development :: Libraries :: Python Modules
Requires-Python: >=3.9
License-File: LICENSE
Requires-Dist: requests>=2.30.0
Requires-Dist: pydantic>=2.3.0
Dynamic: license-file
